baselime/opentelemetry/__init__.py
baselime/opentelemetry/distro.py
baselime/opentelemetry/lambda_instrumentation.py
baselime/opentelemetry/options.py
baselime/opentelemetry/resource.py
baselime/opentelemetry/trace.py
baselime/opentelemetry/utils.py
baselime_opentelemetry-0.2.14.dist-info/METADATA
baselime_opentelemetry-0.2.14.dist-info/WHEEL
baselime_opentelemetry-0.2.14.dist-info/entry_points.txt
baselime_opentelemetry-0.2.14.dist-info/RECORD
