Metadata-Version: 2.1
Name: baselime-opentelemetry
Version: 0.2.14
Summary: 
Author: Ankcorn
Author-email: thomasankcorn@gmail.com
Requires-Python: >=3.7.2,<4.0
Classifier: Programming Language :: Python :: 3
Classifier: Programming Language :: Python :: 3.8
Classifier: Programming Language :: Python :: 3.9
Classifier: Programming Language :: Python :: 3.10
Classifier: Programming Language :: Python :: 3.11
Classifier: Programming Language :: Python :: 3.12
Requires-Dist: opentelemetry-api (>=1.21.0,<2.0.0)
Requires-Dist: opentelemetry-exporter-otlp (>=1.21.0,<2.0.0)
Requires-Dist: opentelemetry-instrumentation (>=0.42b0,<0.43)
Requires-Dist: opentelemetry-sdk (>=1.21.0,<2.0.0)
